{
  "issues": [],
  "warnings": [
    "Node 'file:.commitlintrc.js' has no edges (orphan)",
    "Node 'file:.gitmodules' has no edges (orphan)"
  ],
  "stats": {
    "totalNodes": 262,
    "totalEdges": 419,
    "totalLayers": 10,
    "tourSteps": 12,
    "nodeTypes": {
      "file": 89,
      "class": 28,
      "function": 60,
      "table": 24,
      "config": 25,
      "document": 8,
      "endpoint": 23,
      "service": 5
    },
    "edgeTypes": {
      "imports": 113,
      "contains": 137,
      "exports": 48,
      "tested_by": 11,
      "calls": 30,
      "inherits": 4,
      "depends_on": 22,
      "related": 14,
      "migrates": 3,
      "configures": 22,
      "documents": 13,
      "provisions": 1,
      "deploys": 1
    }
  }
}